{
  "productos": [
    {
      "codigo_de_barras": "559137894",
      "nombre": "Logitech G203",
      "descripcion": "Mouse alámbrico para computadora",
      "imagen_del_producto": "https://m.media-amazon.com/images/I/61UxfXTUyvL._AC_SS450_.jpg",
      "precio_de_venta": 379,
      "cantidad": 4,
      "categoria": 85,
      "id": 85,
      "idVenta": 89,
      "id_del_producto": 85,
      "nombre_del_producto": 85
    },
    {
      "codigo_de_barras": "65652641",
      "nombre": "Logitech G305",
      "descripcion": "Mouse inalámbrico para computadora",
      "imagen_del_producto": "https://m.media-amazon.com/images/I/51VpABY-b6L._AC_SL1500_.jpg",
      "precio_de_venta": 905,
      "cantidad": 7,
      "categoria": 85,
      "id": 86,
      "idVenta": 90,
      "id_del_producto": 86,
      "nombre_del_producto": 86
    },
    {
      "codigo_de_barras": "48456189746",
      "nombre": "Corsair 5000D",
      "descripcion": "Gabinete ATX con vidrio templado",
      "imagen_del_producto": "https://sharkgaming.dk/media/catalog/product/cache/23819f9b0cb4e56225015e135067f902/5/0/5000d-af-black2.png",
      "precio_de_venta": 2790,
      "cantidad": 1,
      "categoria": 88,
      "id": 87,
      "idVenta": 91,
      "id_del_producto": 87,
      "nombre_del_producto": 87
    },
    {
      "codigo_de_barras": "5649841651",
      "nombre": "Acer V266HQL",
      "descripcion": "Monitor de 21.5 pulgadas",
      "imagen_del_producto": "https://http2.mlstatic.com/D_NQ_NP_934813-MLA45731187398_042021-O.jpg",
      "precio_de_venta": 2000,
      "cantidad": 2,
      "categoria": 87,
      "id": 88
    },
    {
      "codigo_de_barras": "165116516",
      "nombre": "ASUS Z590-P ATX",
      "descripcion": "Motherboard ATX socket LGA 1200",
      "imagen_del_producto": "https://m.media-amazon.com/images/I/81q-WnFQcEL._AC_SY355_.jpg",
      "precio_de_venta": 2799,
      "cantidad": 8,
      "categoria": 90,
      "id": 89,
      "idVenta": 87,
      "id_del_producto": 89,
      "nombre_del_producto": 89
    },
    {
      "codigo_de_barras": "15165486",
      "nombre": "Kingston Fury Beast DDR4 3200MHZ 8GB",
      "descripcion": "Stick de 8GB a 3200Mhz",
      "imagen_del_producto": "https://media.kingston.com/kingston/product/ktc-product-memory-beast-ddr4-single-1-zm-lg.jpg",
      "precio_de_venta": 359,
      "cantidad": 2,
      "id": 90,
      "categoria": 91,
      "idVenta": 88,
      "id_del_producto": 90,
      "nombre_del_producto": 90
    },
    {
      "codigo_de_barras": "25484565156",
      "nombre": "Corsair K70 RGB Mk. 2",
      "descripcion": "Teclado mecánico",
      "imagen_del_producto": "https://m.media-amazon.com/images/I/71hdk4PnJFL._AC_SY450_.jpg",
      "precio_de_venta": 3406,
      "cantidad": 1,
      "categoria": 86,
      "id": 91,
      "idVenta": 85,
      "id_del_producto": 91,
      "nombre_del_producto": 91
    }
  ],
  "empleados": [
    {
      "apellido_materno": "Buenrostro",
      "apellido_paterno": "Fajes",
      "curp": "FABM770222MMSJNR00",
      "fecha_ini": "17/05/2023",
      "fecha_nac": "10/05/1993",
      "no_tel": "555555555",
      "nombre": "Margarita",
      "rfc": "FABM770222MM4",
      "sexo": "Femenino",
      "id": 85
    },
    {
      "apellido_materno": "Martinez",
      "apellido_paterno": "Falcon",
      "curp": "FAML781110MTSLRN02",
      "fecha_ini": "17/05/2023",
      "fecha_nac": "27/06/1969",
      "no_tel": "-",
      "nombre": "Leonor",
      "rfc": "FAML781110MT4",
      "sexo": "Femenino",
      "id": 86
    },
    {
      "apellido_materno": "Samaniego",
      "apellido_paterno": "Flores",
      "curp": "FOSL900415HMSLLS01",
      "fecha_ini": "17/05/2023",
      "fecha_nac": "25/11/1987",
      "no_tel": "-",
      "nombre": "Luis Miguel",
      "rfc": "FOSL900415HM9",
      "sexo": "Masculino",
      "id": 87
    },
    {
      "apellido_materno": "Caralampio",
      "apellido_paterno": "Nájera",
      "curp": "NACE981225HMSJRV08",
      "fecha_ini": "17/05/2023",
      "fecha_nac": "12/08/1993",
      "no_tel": "-",
      "nombre": "Ever Abiel",
      "rfc": "NACE981225HM3",
      "sexo": "Masculino",
      "id": 88
    },
    {
      "apellido_materno": "Torres",
      "apellido_paterno": "Urueña",
      "curp": "UUTI521105MMSRRS16",
      "fecha_ini": "17/05/2023",
      "fecha_nac": "24/08/1983",
      "no_tel": "-",
      "nombre": "Maria Isabel",
      "rfc": "UUTI521105MM9",
      "sexo": "Femenino",
      "id": 89
    },
    {
      "apellido_materno": "Victoriano",
      "apellido_paterno": "Delgado",
      "curp": "DEVC841015HMSLCR04",
      "fecha_ini": "17/05/2023",
      "fecha_nac": "18/08/1989",
      "no_tel": "-",
      "nombre": "Cirilio",
      "rfc": "DEVC841015HM5",
      "sexo": "Masculino",
      "id": 90
    },
    {
      "apellido_materno": "Guadarrama",
      "apellido_paterno": "Dominguez",
      "curp": "DOGR980813HMSMDC08",
      "fecha_ini": "17/05/2023",
      "fecha_nac": "28/08/1986",
      "no_tel": "-",
      "nombre": "Ricardo",
      "rfc": "DOGR980813HM3",
      "sexo": "Masculino",
      "id": 91
    }
  ],
  "proveedores": [
    {
      "nombre": "Logitech",
      "nombre_empresa": "Logitech",
      "email": "Logitech@correo.com.mx",
      "telefono": "554160335",
      "direccion": "Av. Santa Fe # 440 - 102, Century Plaza, Santa Fe, Mexico DF, 05348",
      "direccion_facturacion": "Av. Santa Fe # 440 - 102, Century Plaza, Santa Fe, Mexico DF, 05348",
      "forma_pago": 87,
      "id": 85
    },
    {
      "nombre": "Cooler Master",
      "nombre_empresa": "Cooler Master",
      "email": "VENTAS@INTERCOMPRAS.COM",
      "telefono": "01 800-099-6868",
      "direccion": "Avenida Tamaulipas 34, CP. 83000",
      "direccion_facturacion": "Avenida Tamaulipas 34, CP. 83000",
      "forma_pago": 86,
      "id": 86
    },
    {
      "nombre": "Acer",
      "nombre_empresa": "Acer",
      "email": "-",
      "telefono": "55-5999-9400",
      "direccion": "Blvd. Adolfo Ruiz Cortínez 3720, Torre 2, piso 9, suite B111; Jardines del Pedregal; Álvaro Obregón; 01900; Ciudad de México.",
      "direccion_facturacion": "Blvd. Adolfo Ruiz Cortínez 3720, Torre 2, piso 9, suite B111; Jardines del Pedregal; Álvaro Obregón; 01900; Ciudad de México.",
      "forma_pago": 86,
      "id": 87
    },
    {
      "nombre": "Corsair",
      "nombre_empresa": "Corsair",
      "email": "-",
      "telefono": "+1 510-657-8747",
      "direccion": "115 N. McCarthy Blvd. Milpitas, CA 95035",
      "direccion_facturacion": "115 N. McCarthy Blvd. Milpitas, CA 95035",
      "forma_pago": 87,
      "id": 88
    },
    {
      "nombre": "Steren",
      "nombre_empresa": "Steren",
      "email": "-",
      "telefono": "55 1516 6000",
      "direccion": "Electrónica Steren S.A. de C.V con domicilio en: Biólogo Maximino Martínez No. 3408, Col. San Salvador Xochimanca, Deleg. Azcapotzalco, México D. F., C.P. 02870",
      "direccion_facturacion": "Electrónica Steren S.A. de C.V con domicilio en: Biólogo Maximino Martínez No. 3408, Col. San Salvador Xochimanca, Deleg. Azcapotzalco, México D. F., C.P. 02870",
      "forma_pago": 88,
      "id": 89
    },
    {
      "nombre": "HP",
      "nombre_empresa": "HP",
      "email": "-",
      "telefono": "81 47 38 98 74",
      "direccion": "Computing and Printing Global Services Mexico, S. de R.L. de C.V.  Calzada del Valle n 116 A  Monterrey, Nuevo León  C.P.66260, Mexico",
      "direccion_facturacion": "Computing and Printing Global Services Mexico, S. de R.L. de C.V.  Calzada del Valle n 116 A  Monterrey, Nuevo León  C.P.66260, Mexico",
      "forma_pago": 87,
      "id": 90
    },
    {
      "nombre": "Apple",
      "nombre_empresa": "Apple",
      "email": "-",
      "telefono": "6830000",
      "direccion": "Calzada Adolfo López Mateos 861 Mexicali, BCN, 21100",
      "direccion_facturacion": "Calzada Adolfo López Mateos 861 Mexicali, BCN, 21100",
      "forma_pago": 85,
      "id": 91
    }
  ],
  "pagos": [
    {
      "descripcion": "Efectivo",
      "id": 85
    },
    {
      "descripcion": "Tarjeta de crédito",
      "id": 86
    },
    {
      "descripcion": "Tarjeta de débito",
      "id": 87
    },
    {
      "descripcion": "Transferencia bancaria",
      "id": 88
    },
    {
      "descripcion": "Cheque",
      "id": 89
    },
    {
      "descripcion": "Moneda virtual",
      "id": 90
    },
    {
      "descripcion": "Tarjeta de comercio",
      "id": 91
    }
  ],
  "ventas": [
    {
      "fecha_venta": "17/05/2023",
      "mes": 5,
      "empleado": 85,
      "id": 85,
      "terminada": true
    },
    {
      "fecha_venta": "17/05/2023",
      "mes": 5,
      "empleado": 89,
      "id": 86,
      "terminada": true
    },
    {
      "fecha_venta": "17/05/2023",
      "mes": 5,
      "empleado": 90,
      "id": 87
    },
    {
      "fecha_venta": "17/05/2023",
      "mes": 5,
      "empleado": 88,
      "id": 88,
      "terminada": true
    },
    {
      "fecha_venta": "17/05/2023",
      "mes": 5,
      "empleado": 87,
      "id": 89,
      "terminada": true
    },
    {
      "fecha_venta": "17/05/2023",
      "mes": 5,
      "empleado": 90,
      "id": 90,
      "terminada": true
    },
    {
      "fecha_venta": "17/05/2023",
      "mes": 5,
      "empleado": 91,
      "id": 91,
      "terminada": true
    }
  ],
  "ventas_productos": [
    {
      "idVenta": 85,
      "id_del_producto": 85,
      "categoria": 85,
      "nombre_del_producto": 85,
      "cantidad": 2,
      "codigo_de_barras": "559137894",
      "id": 1
    },
    {
      "idVenta": 85,
      "id_del_producto": 91,
      "categoria": 86,
      "nombre_del_producto": 91,
      "cantidad": 1,
      "codigo_de_barras": "25484565156",
      "id": 2
    },
    {
      "idVenta": 86,
      "id_del_producto": 85,
      "categoria": 85,
      "nombre_del_producto": 85,
      "cantidad": 1,
      "codigo_de_barras": "559137894",
      "id": 3
    },
    {
      "idVenta": 88,
      "id_del_producto": 90,
      "categoria": 91,
      "nombre_del_producto": 90,
      "cantidad": 2,
      "codigo_de_barras": "15165486",
      "id": 4
    },
    {
      "idVenta": 89,
      "id_del_producto": 85,
      "categoria": 85,
      "nombre_del_producto": 85,
      "cantidad": 1,
      "codigo_de_barras": "559137894",
      "id": 5
    },
    {
      "idVenta": 90,
      "id_del_producto": 86,
      "categoria": 85,
      "nombre_del_producto": 86,
      "cantidad": 3,
      "codigo_de_barras": "65652641",
      "id": 6
    },
    {
      "idVenta": 91,
      "id_del_producto": 87,
      "categoria": 88,
      "nombre_del_producto": 87,
      "cantidad": 1,
      "codigo_de_barras": "48456189746",
      "id": 7
    }
  ],
  "categorias": [
    {
      "descripcion": "Ratones",
      "id": 85
    },
    {
      "descripcion": "Teclados",
      "id": 86
    },
    {
      "descripcion": "Monitores",
      "id": 87
    },
    {
      "descripcion": "Gabinetes",
      "id": 88
    },
    {
      "descripcion": "Disipadores",
      "id": 89
    },
    {
      "descripcion": "Motherboards",
      "id": 90
    },
    {
      "descripcion": "Módulos de memoria RAM",
      "id": 91
    }
  ],
  "pedidos": [
    {
      "productos": 85,
      "cantidad": 3,
      "proveedor": 85,
      "pago": 85,
      "estatus": "Entregado",
      "id": 85
    },
    {
      "productos": 87,
      "cantidad": 1,
      "proveedor": 88,
      "pago": 86,
      "estatus": "Autorizado",
      "id": 86
    },
    {
      "productos": 88,
      "cantidad": 2,
      "proveedor": 87,
      "pago": 88,
      "estatus": "Autorizado",
      "id": 87
    },
    {
      "productos": 86,
      "cantidad": 4,
      "proveedor": 85,
      "pago": 85,
      "estatus": "Entregado",
      "id": 88
    },
    {
      "productos": 91,
      "cantidad": 1,
      "proveedor": 88,
      "pago": 90,
      "estatus": "Autorizado",
      "id": 89
    },
    {
      "productos": 89,
      "cantidad": 4,
      "proveedor": 89,
      "pago": 85,
      "estatus": "Entregado",
      "id": 90
    },
    {
      "productos": 86,
      "cantidad": 12,
      "proveedor": 85,
      "pago": 85,
      "estatus": "Autorizado",
      "id": 91
    }
  ]
}